dawnet_client/__init__.py
dawnet_client/config.py
dawnet_client/core.py
dawnet_client/decorators.py
dawnet_client/dn_tracer.py
dawnet_client/file_uploader.py
dawnet_client/output/__init__.py
dawnet_client/output/results_handler.py
dawnet_client/utils/__init__.py
dawnet_client/utils/audio_utils.py
dawnet_client/utils/file_type_classifier.py
tests/__init__.py
tests/_test_audio_utils.py
tests/test_audio_utils.py
tests/test_core.py
tests/test_registration.py
tests/test_results_handler.py
dawnet_client-0.7.3.dist-info/LICENSE.md
dawnet_client-0.7.3.dist-info/METADATA
dawnet_client-0.7.3.dist-info/WHEEL
dawnet_client-0.7.3.dist-info/entry_points.txt
dawnet_client-0.7.3.dist-info/top_level.txt
dawnet_client-0.7.3.dist-info/RECORD
