Metadata-Version: 2.1
Name: dawnet-client
Version: 0.7.3
Summary: DAWNet client enables remote execution of python code triggered from a DAW.
Home-page: https://dawnet.tools
Author: Steve Hiehn
Author-email: stevehiehn@gmail.com
Requires-Python: >=3.6
License-File: LICENSE.md
Requires-Dist: aiohttp
Requires-Dist: websockets
Requires-Dist: nest-asyncio
Requires-Dist: sentry-sdk
Requires-Dist: pydub
Requires-Dist: librosa
Requires-Dist: pytest-asyncio
